{"chunk_definitions":[{"row":226,"row_count":1,"visible":true,"expansion_state":0,"options":{"engine":"r","label":"unnamed-chunk-4","dev":"png"},"document_id":"55CE4F6A","chunk_id":"cs0xu66cwi9o5","chunk_label":"unnamed-chunk-1"},{"row":262,"row_count":1,"visible":true,"expansion_state":0,"options":{"engine":"r","label":"unnamed-chunk-5","dev":"png"},"document_id":"55CE4F6A","chunk_id":"ceuu22gtc1nlx","chunk_label":"unnamed-chunk-2"},{"row":283,"row_count":1,"visible":true,"expansion_state":0,"options":{"engine":"r","label":"unnamed-chunk-6","dev":"png"},"document_id":"55CE4F6A","chunk_id":"c3vs5t5fqttqt","chunk_label":"unnamed-chunk-3"},{"row":310,"row_count":1,"visible":true,"expansion_state":0,"options":{"engine":"r","label":"unnamed-chunk-7","dev":"png"},"document_id":"55CE4F6A","chunk_id":"c4l9ojpccsheh","chunk_label":"unnamed-chunk-4"},{"row":317,"row_count":1,"visible":true,"expansion_state":0,"options":{"engine":"r","label":"unnamed-chunk-8","dev":"png"},"document_id":"55CE4F6A","chunk_id":"c5ulki9cdumae","chunk_label":"unnamed-chunk-5"},{"row":326,"row_count":1,"visible":true,"expansion_state":0,"options":{"engine":"r","label":"unnamed-chunk-9","dev":"png"},"document_id":"55CE4F6A","chunk_id":"cvu3lnq4os8h6","chunk_label":"unnamed-chunk-6"},{"row":336,"row_count":1,"visible":true,"expansion_state":0,"options":{"engine":"r","label":"unnamed-chunk-17","dev":"png"},"document_id":"55CE4F6A","chunk_id":"c9sqrdew005oy","chunk_label":"unnamed-chunk-7"}],"doc_write_time":1755859287}